MANIFEST.in
setup.cfg
setup.py
openshift_under_kubernetes/__init__.py
openshift_under_kubernetes/cli.py
openshift_under_kubernetes/more_objects.py
openshift_under_kubernetes/os_kube.py
openshift_under_kubernetes/util.py
openshift_under_kubernetes.egg-info/PKG-INFO
openshift_under_kubernetes.egg-info/SOURCES.txt
openshift_under_kubernetes.egg-info/dependency_links.txt
openshift_under_kubernetes.egg-info/entry_points.txt
openshift_under_kubernetes.egg-info/not-zip-safe
openshift_under_kubernetes.egg-info/requires.txt
openshift_under_kubernetes.egg-info/top_level.txt
openshift_under_kubernetes/resources/__init__.py
openshift_under_kubernetes/resources/scripts/__init__.py
openshift_under_kubernetes/resources/scripts/create-config.sh