Metadata-Version: 1.1
Name: openshift-under-kubernetes
Version: 1.2.8
Summary: Deploys OpenShift Origin to an existing Kubernetes cluster.
Home-page: https://github.com/paralin/openshift-under-kubernetes
Author: Christian Stewart
Author-email: christian@paral.in
License: BSD
Platform: any
Classifier: Development Status :: 4 - Beta
Classifier: Environment :: Console
Classifier: Intended Audience :: Developers
Classifier: License :: OSI Approved :: BSD License
Classifier: Operating System :: POSIX
Classifier: Operating System :: MacOS
Classifier: Operating System :: Unix
Classifier: Operating System :: Microsoft :: Windows
Classifier: Programming Language :: Python
Classifier: Programming Language :: Python :: 2
Classifier: Programming Language :: Python :: 3
Classifier: Topic :: Software Development :: Libraries :: Python Modules
